ucalcs/__init__.py
ucalcs/basics.py
ucalcs-0.1.3.dist-info/entry_points.txt
ucalcs-0.1.3.dist-info/WHEEL
ucalcs-0.1.3.dist-info/METADATA
ucalcs-0.1.3.dist-info/RECORD
